noa/__init__.py
noa/lagged_offline_noa.py
noa/noa.py
noa/offline_noa.py
noa/alignment/__init__.py
noa/alignment/_numba.py
noa/alignment/runtime_cache.py
noa/baseline/__init__.py
noa/baseline/baseline_system.py
noa/baseline/lagged_baseline_system.py
noa/baseline/match-0.9.4.jar
noa/baseline/match.py
realtime_accompaniment-1.0.0.dist-info/licenses/LICENSE
tsm/__init__.py
tsm/offline_tsm.py
tsm/tsm.py
utils/__init__.py
utils/audio.py
utils/audio_streamer.py
utils/buffer.py
utils/cache_utils.py
utils/clean_cache.py
utils/constants.py
utils/latency_tester.py
utils/mode_detection.py
utils/numeric.py
utils/presets.py
utils/evaluation/__init__.py
utils/evaluation/evaluation.py
utils/evaluation/generate_query.py
utils/evaluation/onset_detection.py
realtime_accompaniment-1.0.0.dist-info/METADATA
realtime_accompaniment-1.0.0.dist-info/WHEEL
realtime_accompaniment-1.0.0.dist-info/entry_points.txt
realtime_accompaniment-1.0.0.dist-info/top_level.txt
realtime_accompaniment-1.0.0.dist-info/RECORD
