Metadata-Version: 2.4
Name: realtime-accompaniment
Version: 1.0.0
Summary: A real-time musical accompaniment system that dynamically adjusts orchestral playback speed
Home-page: https://github.com/yourusername/RealtimeAccompaniment
Author: RealtimeAccompaniment Team
Author-email: your-email@example.com
Maintainer: RealtimeAccompaniment Team
License: MIT
Project-URL: Homepage, https://github.com/yourusername/RealtimeAccompaniment
Project-URL: Repository, https://github.com/yourusername/RealtimeAccompaniment
Project-URL: Documentation, https://github.com/yourusername/RealtimeAccompaniment#readme
Project-URL: Issues, https://github.com/yourusername/RealtimeAccompaniment/issues
Keywords: music,audio,real-time,accompaniment,alignment,time-stretching
Classifier: Development Status :: 4 - Beta
Classifier: Intended Audience :: Developers
Classifier: Intended Audience :: Science/Research
Classifier: License :: OSI Approved :: MIT License
Classifier: Operating System :: OS Independent
Classifier: Programming Language :: Python :: 3
Classifier: Programming Language :: Python :: 3.7
Classifier: Programming Language :: Python :: 3.8
Classifier: Programming Language :: Python :: 3.9
Classifier: Programming Language :: Python :: 3.10
Classifier: Programming Language :: Python :: 3.11
Classifier: Topic :: Multimedia :: Sound/Audio
Classifier: Topic :: Scientific/Engineering :: Artificial Intelligence
Requires-Python: >=3.7
License-File: LICENSE
Requires-Dist: numpy
Requires-Dist: scipy
Requires-Dist: librosa
Requires-Dist: matplotlib
Requires-Dist: pyaudio
Requires-Dist: numba
Requires-Dist: plotly
Requires-Dist: ipython
Provides-Extra: dev
Requires-Dist: pytest; extra == "dev"
Requires-Dist: pytest-cov; extra == "dev"
Requires-Dist: black; extra == "dev"
Requires-Dist: flake8; extra == "dev"
Requires-Dist: mypy; extra == "dev"
Provides-Extra: test
Requires-Dist: pytest; extra == "test"
Requires-Dist: pytest-cov; extra == "test"
Dynamic: license-file
